pythonic_fp/singletons/__init__.py
pythonic_fp/singletons/nada.py
pythonic_fp/singletons/novalue.py
pythonic_fp/singletons/py.typed
pythonic_fp/singletons/sbool.py
pythonic_fp/singletons/sentinel.py
pythonic_fp_singletons-1.0.0.dist-info/licenses/LICENSE
pythonic_fp_singletons-1.0.0.dist-info/WHEEL
pythonic_fp_singletons-1.0.0.dist-info/METADATA
pythonic_fp_singletons-1.0.0.dist-info/RECORD
