Metadata-Version: 2.4
Name: pythonic-fp-singletons
Version: 1.0.0
Summary: Singletons.
Keywords: singleton,sentinel
Author-email: "Geoffrey R. Scheller" <geoffrey@scheller.com>
Requires-Python: >=3.12
Classifier: Development Status :: 4 - Beta
Classifier: Framework :: Pytest
Classifier: Intended Audience :: Developers
Classifier: License :: OSI Approved :: Apache Software License
Classifier: Operating System :: OS Independent
Classifier: Programming Language :: Python :: 3.13
Classifier: Typing :: Typed
License-File: LICENSE
Requires-Dist: pytest>=8.4.1 ; extra == "test"
Requires-Dist: pythonic-fp-circulararray>=5.3.0 ; extra == "test"
Project-URL: Changelog, https://github.com/grscheller/pythonic-fp-singletons/blob/main/CHANGELOG.rst
Project-URL: Documentation, https://grscheller.github.io/pythonic-fp/singletons/development/build/html/releases.html
Project-URL: Homepage, https://github.com/grscheller/pythonic-fp/blob/main/README.md
Project-URL: Source, https://github.com/grscheller/pythonic-fp-singletons
Provides-Extra: test
